abeja/__init__.py
abeja/base_client.py
abeja/common/__init__.py
abeja/common/api_client.py
abeja/common/auth.py
abeja/common/config.py
abeja/common/connection.py
abeja/common/docker_image_name.py
abeja/common/exec_env.py
abeja/common/file_factory.py
abeja/common/file_helpers.py
abeja/common/http_file.py
abeja/common/instance_type.py
abeja/common/iterator.py
abeja/common/local_file.py
abeja/common/logging.py
abeja/common/s3etag.py
abeja/common/source_data.py
abeja/common/utils.py
abeja/contrib/__init__.py
abeja/contrib/keras/__init__.py
abeja/contrib/keras/callbacks.py
abeja/datalake/__init__.py
abeja/datalake/api/__init__.py
abeja/datalake/api/client.py
abeja/datalake/channel.py
abeja/datalake/client.py
abeja/datalake/file.py
abeja/datalake/metadata.py
abeja/datalake/storage_type.py
abeja/datasets/__init__.py
abeja/datasets/api/__init__.py
abeja/datasets/api/client.py
abeja/datasets/base.py
abeja/datasets/client.py
abeja/datasets/dataset.py
abeja/datasets/dataset_item.py
abeja/deployments/__init__.py
abeja/deployments/api/__init__.py
abeja/deployments/api/client.py
abeja/endpoints/__init__.py
abeja/endpoints/api/__init__.py
abeja/endpoints/api/client.py
abeja/exceptions/__init__.py
abeja/models/__init__.py
abeja/models/api/__init__.py
abeja/models/api/client.py
abeja/notebook/__init__.py
abeja/notebook/api/__init__.py
abeja/notebook/api/client.py
abeja/notebook/types.py
abeja/opsbeellm/dataset/__init__.py
abeja/opsbeellm/dataset/api/__init__.py
abeja/opsbeellm/dataset/api/client.py
abeja/opsbeellm/deployment/__init__.py
abeja/opsbeellm/deployment/api/__init__.py
abeja/opsbeellm/deployment/api/client.py
abeja/opsbeellm/history/__init__.py
abeja/opsbeellm/history/api/__init__.py
abeja/opsbeellm/history/api/client.py
abeja/registry/__init__.py
abeja/registry/api/__init__.py
abeja/registry/api/client.py
abeja/runs/__init__.py
abeja/runs/api/__init__.py
abeja/runs/api/client.py
abeja/secret/__init__.py
abeja/secret/api/__init__.py
abeja/secret/api/client.py
abeja_sdk-2.3.5.dist-info/LICENSE
abeja_sdk-2.3.5.dist-info/WHEEL
abeja_sdk-2.3.5.dist-info/METADATA
abeja_sdk-2.3.5.dist-info/RECORD
