Metadata-Version: 2.1
Name: abeja-sdk
Version: 2.3.5
Summary: ABEJA Platform Software Development Kit
License: Apache-2.0
Author: ABEJA Inc.
Author-email: platform-support@abejainc.com
Requires-Python: >=3.8,<3.12
Classifier: Development Status :: 3 - Alpha
Classifier: Intended Audience :: Developers
Classifier: License :: OSI Approved :: Apache Software License
Classifier: Operating System :: OS Independent
Classifier: Programming Language :: Python :: 3
Classifier: Programming Language :: Python :: 3.8
Classifier: Programming Language :: Python :: 3.9
Classifier: Programming Language :: Python :: 3.10
Classifier: Programming Language :: Python :: 3.11
Classifier: Programming Language :: Python :: 3.10
Classifier: Programming Language :: Python :: 3.11
Classifier: Programming Language :: Python :: 3.8
Classifier: Programming Language :: Python :: 3.9
Classifier: Topic :: Internet :: WWW/HTTP
Provides-Extra: docs
Requires-Dist: Sphinx (==3.4.0); extra == "docs"
Requires-Dist: guzzle_sphinx_theme (==0.7.11); extra == "docs"
Requires-Dist: importlib-metadata (>=2.0.0,<3.0.0); extra == "docs"
Requires-Dist: jinja2 (==3.0.3); extra == "docs"
Requires-Dist: protobuf (>=3.20.2,<6.0.0)
Requires-Dist: requests (>=2.27.1)
Requires-Dist: retrying (==1.3.4)
Requires-Dist: tensorboardx (>=2.6.1,<3.0.0)
Requires-Dist: tomlkit (>=0.7.0,<1.0.0)
Requires-Dist: virtualenv (==20.0.34); extra == "docs"
